deltares_datasuite/__init__.py
deltares_datasuite/client/__init__.py
deltares_datasuite/client/dms_client.py
deltares_datasuite/core/__init__.py
deltares_datasuite/core/models/__init__.py
deltares_datasuite/core/models/item.py
deltares_datasuite-0.5.0.dist-info/LICENSE
deltares_datasuite-0.5.0.dist-info/METADATA
deltares_datasuite-0.5.0.dist-info/WHEEL
deltares_datasuite-0.5.0.dist-info/RECORD
