Metadata-Version: 2.1
Name: deltares_datasuite
Version: 0.5.0
Summary: Python package to create and update STAC items in the Deltares Data Management Suite
Home-page: https://datasuite.deltares.nl
License: MIT
Author: Deltares
Author-email: nathan.clerks@deltares.nl
Maintainer: Deltares
Maintainer-email: nathan.clerks@deltares.nl
Requires-Python: >=3.9,<3.12
Classifier: Development Status :: 3 - Alpha
Classifier: Intended Audience :: Developers
Classifier: License :: OSI Approved :: MIT License
Classifier: Operating System :: OS Independent
Classifier: Programming Language :: Python :: 3
Classifier: Programming Language :: Python :: 3.9
Classifier: Programming Language :: Python :: 3.10
Classifier: Programming Language :: Python :: 3.11
Classifier: Topic :: Software Development :: Libraries :: Python Modules
Requires-Dist: geojson (>=3.0.1,<4.0.0)
Requires-Dist: pystac (>=1.8.4,<2.0.0)
Requires-Dist: python-dotenv (>=1.0.0,<2.0.0)
Requires-Dist: requests (>=2.31.0,<3.0.0)
Requires-Dist: types-requests (>=2.31.0.10,<3.0.0.0)
Project-URL: Documentation, https://datasuite.deltares.nl/docs
Project-URL: Repository, https://github.com/Deltares-research/data-management-suite
